analysis/__init__.py
analysis/aligners.py
analysis/coordinate_mapper.py
analysis/read_editor.py
analysis/read_preprocessor.py
analysis/references.py
analysis/seq_utils.py
analysis/variant_caller.py
core_utils/__init__.py
core_utils/feature_file_utils.py
core_utils/file_utils.py
core_utils/string_utils.py
core_utils/vcf_utils.py
satmut_utils/__init__.py
satmut_utils/definitions.py
satmut_utils/satmut_utils.py
scripts/__init__.py
scripts/run_bowtie2_aligner.py
scripts/run_fastq_preprocessor.py
tests/__init__.py
tests/analysis/__init__.py
tests/analysis/test_aligners.py
tests/analysis/test_coordinate_mapper.py
tests/analysis/test_read_editor.py
tests/analysis/test_read_preprocessor.py
tests/analysis/test_references.py
tests/analysis/test_seq_utils.py
tests/analysis/test_variant_caller.py
tests/core_utils/__init__.py
tests/core_utils/test_feature_file_utils.py
tests/core_utils/test_file_utils.py
tests/core_utils/test_string_utils.py
tests/test_data/CBS.fa
tests/test_data/CBS.gff
tests/test_data/CBS_pEZY3.fa
tests/test_data/CBS_pEZY3.fa.1.bt2
tests/test_data/CBS_pEZY3.fa.2.bt2
tests/test_data/CBS_pEZY3.fa.3.bt2
tests/test_data/CBS_pEZY3.fa.4.bt2
tests/test_data/CBS_pEZY3.fa.fai
tests/test_data/CBS_pEZY3.fa.rev.1.bt2
tests/test_data/CBS_pEZY3.fa.rev.2.bt2
tests/test_data/CBS_pEZY3.gff
tests/test_data/CBS_pEZY3_primers.bed
tests/test_data/CBS_pEZY3_targets.bed
tests/test_data/CBS_sim.R1.fq.gz
tests/test_data/CBS_sim.R2.fq.gz
tests/test_data/CBS_sim.bam
tests/test_data/CBS_sim.bam.bai
tests/test_data/CBS_sim.vcf
tests/test_data/CBS_sim_primers.bed
tests/test_data/GRCh38.chr21.fa.gz
tests/test_data/PKNOX1.fa
tests/test_data/__init__.py
tests/test_data/appris_human_24_01_2019_selected.fa
tests/test_data/appris_human_24_01_2019_selected.fa.fai
tests/test_data/appris_human_v1_actual_regions_contigs.txt
tests/test_data/appris_human_v1_actual_regions_gene_ids.txt
tests/test_data/appris_human_v1_actual_regions_trx_ids.txt
tests/test_data/gencode.v29.annotation.gtf
satmut_utils-1.1.2.dist-info/LICENSE.txt
satmut_utils-1.1.2.dist-info/METADATA
satmut_utils-1.1.2.dist-info/WHEEL
satmut_utils-1.1.2.dist-info/entry_points.txt
satmut_utils-1.1.2.dist-info/top_level.txt
satmut_utils-1.1.2.dist-info/RECORD
