Metadata-Version: 2.1
Name: satmut-utils
Version: 1.1.2
Summary: Tools for variant simulation and variant calling in paired end, targeted sequencing saturation mutagenesis experiments
Home-page: https://github.com/CenikLab/satmut_utils
Author: Ian Hoskins
Author-email: ianjameshoskins@utexas.edu
Project-URL: Bug Tracker, https://github.com/CenikLab/satmut_utils/issues
Classifier: Development Status :: 4 - Beta
Classifier: License :: OSI Approved :: GNU General Public License v3 (GPLv3)
Classifier: Operating System :: MacOS :: MacOS X
Classifier: Operating System :: POSIX :: Linux
Classifier: Programming Language :: Python
Classifier: Programming Language :: Python :: 3
Classifier: Topic :: Scientific/Engineering :: Bio-Informatics
Requires-Python: >=3.7
License-File: LICENSE.txt
